examples/mlx_pipeline_fix.py
langchain_integration_health/__init__.py
langchain_integration_health/cli.py
langchain_integration_health/dashboard/__init__.py
langchain_integration_health/dashboard/app.py
langchain_integration_health/dashboard/components.py
langchain_integration_health/dashboard/data_loader.py
langchain_integration_health/testers/__init__.py
langchain_integration_health/testers/base_tester.py
langchain_integration_health/testers/chat_model_tester.py
langchain_integration_health/testers/embeddings_tester.py
langchain_integration_health/testers/llm_tester.py
langchain_integration_health/utils/__init__.py
langchain_integration_health/utils/config.py
langchain_integration_health/utils/discovery.py
langchain_integration_health/utils/reporters.py
langchain_integration_health-0.1.6.dist-info/licenses/LICENSE
langchain_integration_health-0.1.6.dist-info/METADATA
langchain_integration_health-0.1.6.dist-info/WHEEL
langchain_integration_health-0.1.6.dist-info/entry_points.txt
langchain_integration_health-0.1.6.dist-info/top_level.txt
langchain_integration_health-0.1.6.dist-info/RECORD
