Metadata-Version: 2.4
Name: langchain-integration-health
Version: 0.1.6
Summary: Comprehensive testing framework and dashboard for LangChain integration compatibility
Author: LangChain Integration Health Team
Author-email: Sadiq Khan <sadiqkhzn@example.com>
Maintainer-email: Sadiq Khan <sadiqkhzn@example.com>
License: MIT
Project-URL: Homepage, https://github.com/sadiqkhzn/langchain-integration-health
Project-URL: Repository, https://github.com/sadiqkhzn/langchain-integration-health
Project-URL: Issues, https://github.com/sadiqkhzn/langchain-integration-health/issues
Project-URL: Documentation, https://github.com/sadiqkhzn/langchain-integration-health#readme
Keywords: langchain,testing,integration,compatibility,dashboard
Classifier: Development Status :: 4 - Beta
Classifier: Intended Audience :: Developers
Classifier: License :: OSI Approved :: MIT License
Classifier: Operating System :: OS Independent
Classifier: Programming Language :: Python :: 3
Classifier: Programming Language :: Python :: 3.8
Classifier: Programming Language :: Python :: 3.9
Classifier: Programming Language :: Python :: 3.10
Classifier: Programming Language :: Python :: 3.11
Classifier: Topic :: Software Development :: Testing
Classifier: Topic :: Software Development :: Libraries :: Python Modules
Requires-Python: >=3.8
License-File: LICENSE
Requires-Dist: langchain>=0.1.0
Requires-Dist: langchain-core>=0.1.0
Requires-Dist: streamlit>=1.28.0
Requires-Dist: fastapi>=0.104.0
Requires-Dist: uvicorn>=0.24.0
Requires-Dist: pydantic>=2.0.0
Requires-Dist: pandas>=2.0.0
Requires-Dist: plotly>=5.17.0
Requires-Dist: pytest>=7.4.0
Requires-Dist: pytest-asyncio>=0.21.0
Requires-Dist: aiohttp>=3.9.0
Requires-Dist: sqlalchemy>=2.0.0
Requires-Dist: alembic>=1.12.0
Requires-Dist: typer>=0.9.0
Requires-Dist: rich>=13.6.0
Provides-Extra: dev
Requires-Dist: pytest; extra == "dev"
Requires-Dist: pytest-asyncio; extra == "dev"
Requires-Dist: black; extra == "dev"
Requires-Dist: flake8; extra == "dev"
Requires-Dist: mypy; extra == "dev"
Requires-Dist: pre-commit; extra == "dev"
Dynamic: author
Dynamic: license-file
Dynamic: requires-python
